MANIFEST.in
setup.py
logy/__init__.py
logy/auth.py
logy/core.py
logy/default_settings.py
logy/scripts.py
logy/version.py
logy.egg-info/PKG-INFO
logy.egg-info/SOURCES.txt
logy.egg-info/dependency_links.txt
logy.egg-info/entry_points.txt
logy.egg-info/requires.txt
logy.egg-info/top_level.txt
logy/models/__init__.py
logy/models/database.py
logy/models/tables.py
logy/static/css/style.css
logy/templates/index.html
logy/templates/master.html
logy/templates/view_record.html
logy/views/__init__.py
logy/views/frontend.py
logy/views/sink.py