Metadata-Version: 1.0
Name: logy
Version: 0.1
Summary: A flask based web application for central logging
Home-page: http://bitbucket.org/victorlin/logy
Author: Victor Lin
Author-email: bornstub@gmail.com
License: MIT
Platform: UNKNOWN
